mongofollow.py
mongofollow-1.0.1.dist-info/LICENSE
mongofollow-1.0.1.dist-info/WHEEL
mongofollow-1.0.1.dist-info/METADATA
mongofollow-1.0.1.dist-info/RECORD
